{
  "timestamp": "2025-09-25T22:55:07.098547",
  "device_info": {
    "hostname": "DESKTOP-V0GE4SP",
    "platform": "Windows-10-10.0.19045-SP0",
    "system": "Windows",
    "release": "10"
  },
  "network_info": {
    "hostname": "DESKTOP-V0GE4SP",
    "fqdn": "DESKTOP-V0GE4SP",
    "local_ips": [
      {
        "interface": "{DFE3EA44-D90C-499B-A2C0-DA93CE54106C}",
        "ip": "192.168.20.118",
        "netmask": "255.255.255.0",
        "broadcast": "192.168.20.255"
      }
    ],
    "public_ip": "45.237.214.208",
    "default_gateway": "192.168.20.1",
    "dns_servers": [],
    "wifi_info": null
  },
  "geolocation": {
    "ip": "45.237.214.208",
    "country": "Brazil",
    "region": "GO",
    "city": "Goiânia",
    "latitude": -16.6802,
    "longitude": -49.2564,
    "timezone": "America/Sao_Paulo",
    "isp": "Fresnel Conectividade Eireli ME",
    "as": "AS268303 Fresnel Conectividade Eireli ME",
    "query_time": "2025-09-25T22:55:08.073839",
    "source": "http://ip-api.com/json/45.237.214.208"
  },
  "security_notes": []
}